[
  {
    "hl": "hl-certification-scruminc",
    "institution": "Agile Education",
    "authority": "Scrum Inc.™",
    "startDate": "Dec 2022",
    "endDate": "Dec 2029",
    "name": "Registered Product Owner™",
    "link": "https://s3.amazonaws.com/scruminc-certs/RPO-6785822",
    "certID": "RPO-6785822",
    "alt": "Registered Product Owner™",
    "image": "asserts/images/certification/scruminc.png",
    "width": "120",
    "height": "30"
  },
  {
    "hl": "hl-certification-scruminc",
    "institution": "Agile Education",
    "authority": "Scrum Inc.™",
    "startDate": "Dec 2022",
    "endDate": "Dec 2029",
    "name": "Registered Scrum Master™",
    "link": "https://s3.amazonaws.com/scruminc-certs/RSM-1073004",
    "certID": "RSM-1073004",
    "alt": "Registered Scrum Master™",
    "image": "asserts/images/certification/scruminc.png",
    "width": "120",
    "height": "30"
  },
  {
    "hl": "hl-certification-aws",
    "institution": "Amazon Web Services (AWS)",
    "authority": "Coursera",
    "startDate": "Jul 2025",
    "endDate": "",
    "name": "AWS Cloud Solutions Architect",
    "link": "https://www.coursera.org/account/accomplishments/specialization/061WISA3SUWQ",
    "certID": "061WISA3SUWQ",
    "alt": "AWS Cloud Solutions Architect",
    "image": "asserts/images/certification/aws.png",
    "width": "120",
    "height": "40"
  },
  {
    "hl": "hl-certification-coursera",
    "institution": "Google",
    "authority": "Coursera",
    "startDate": "Feb 2025",
    "endDate": "",
    "name": "Google AI Essentials",
    "link": "https://www.coursera.org/account/accomplishments/records/LC0PE7NLG4F3",
    "certID": "LC0PE7NLG4F3",
    "alt": "Google AI Essentials",
    "image": "asserts/images/certification/coursera.png",
    "width": "120",
    "height": "68"
  },
  {
    "hl": "hl-certification-coursera",
    "institution": "Google",
    "authority": "Coursera",
    "startDate": "Feb 2025",
    "endDate": "",
    "name": "Google Project Management Professional Certificate",
    "link": "https://www.coursera.org/account/accomplishments/specialization/L2M39B5BUD9U",
    "certID": "L2M39B5BUD9U",
    "alt": "Google Project Management Professional Certificate",
    "image": "asserts/images/certification/coursera.png",
    "width": "120",
    "height": "68"
  },
  {
    "hl": "hl-certification-coursera",
    "institution": "北京大學",
    "authority": "Coursera",
    "startDate": "Oct 2025",
    "endDate": "",
    "name": "Management Communication 管理沟通",
    "link": "https://www.coursera.org/account/accomplishments/verify/0I80AVIZCHS5",
    "certID": "0I80AVIZCHS5",
    "alt": "Management Communication 管理沟通",
    "image": "asserts/images/certification/coursera.png",
    "width": "120",
    "height": "68"
  },
  {
    "hl": "hl-certification-coursera",
    "institution": "Google",
    "authority": "Coursera",
    "startDate": "Dec 2025",
    "endDate": "",
    "name": "Google Cybersecurity Specialization",
    "link": "https://www.coursera.org/account/accomplishments/specialization/H1S08K60KZ3P",
    "certID": "H1S08K60KZ3P",
    "alt": "Google Cybersecurity Specialization",
    "image": "asserts/images/certification/coursera.png",
    "width": "120",
    "height": "68"
  },
  {
    "hl": "hl-certification-coursera",
    "institution": "國立臺灣大學",
    "authority": "Coursera",
    "startDate": "Dec 2025",
    "endDate": "",
    "name": "賽局與產業競爭策略 (Game Theory and Business Strategy)",
    "link": "https://www.coursera.org/account/accomplishments/verify/Q9XY4YQY2ZNZ",
    "certID": "Q9XY4YQY2ZNZ",
    "alt": "賽局與產業競爭策略 (Game Theory and Business Strategy)",
    "image": "asserts/images/certification/coursera.png",
    "width": "120",
    "height": "68"
  }
]